{
  "data": [
    {
      "objectType": "title",
      "pos": {
        "x": 630.8421875,
        "y": 521.535934291581
      },
      "size": {
        "x": 112.18677277260639,
        "y": 28.935532233883055
      },
      "titleColor": "#cecae6"
    },
    {
      "objectType": "time",
      "pos": {
        "x": 632.3770833333333,
        "y": 702.9672544080611
      },
      "size": {
        "x": 96.4806245844415,
        "y": 20.25487256371813
      }
    },
    {
      "objectType": "lyric",
      "pos": {
        "x": 631.5,
        "y": 563.664167916042
      },
      "size": {
        "x": 77.98999003336655,
        "y": 19.815195071868573
      },
      "lyricColor": "#4cede4",
      "lyricColor2": "#878583"
    },
    {
      "objectType": "fftGraph",
      "pos": {
        "x": 631.5,
        "y": 274.30884557721134
      },
      "size": {
        "x": 436.0151525206993,
        "y": 435.47221405546816
      },
      "type": "circle"
    },
    {
      "objectType": "fftGraph",
      "pos": {
        "x": 631.5,
        "y": 274.30884557721134
      },
      "size": {
        "x": 431.3930672998835,
        "y": 29.246742187818484
      },
      "type": "waveform"
    },
    {
      "objectType": "text",
      "pos": {
        "x": 631.5,
        "y": 755.3552361396303
      },
      "size": {
        "x": 89.64549322840404,
        "y": 20.125293895047598
      },
      "textInside": "HAU MASTER",
      "textColor": "#503737"
    },
    {
      "objectType": "fftGraph",
      "pos": {
        "x": 631.916601837333,
        "y": 73.41533442165434
      },
      "size": {
        "x": -435.86653700799945,
        "y": -34.044774636759456
      },
      "type": "bottom noColor"
    },
    {
      "objectType": "fftGraph",
      "pos": {
        "x": 631.5,
        "y": 473.5062972292193
      },
      "size": {
        "x": 435.5431804645622,
        "y": 34.478439425051334
      },
      "type": "bottom noColor"
    },
    {
      "objectType": "ButtonShape",
      "pos": {
        "x": 631.5,
        "y": 648.0668896321067
      },
      "size": {
        "x": 121.36640625000001,
        "y": 59.810006433729036
      },
      "name": "Pause"
    },
    {
      "objectType": "ButtonShape",
      "pos": {
        "x": 732.1453125,
        "y": 642.9030100334446
      },
      "size": {
        "x": 70.27630208333333,
        "y": 49.06182404998474
      },
      "name": "Next"
    },
    {
      "objectType": "ButtonShape",
      "pos": {
        "x": 530.8546875,
        "y": 642.9030100334446
      },
      "size": {
        "x": 70.27630208333333,
        "y": 48.799285193364994
      },
      "name": "Pre"
    }
  ],
  "songNow": 31,
  "backgNow": 27,
  "width": 1263,
  "height": 772
}
